fastapi_advertising_prediction/__init__.py
fastapi_advertising_prediction/main.py
fastapi_advertising_prediction/run_train.py
fastapi_advertising_prediction/schemas.py
fastapi_advertising_prediction/train.py
fastapi_advertising_prediction-0.0.7.dist-info/LICENSE
fastapi_advertising_prediction-0.0.7.dist-info/METADATA
fastapi_advertising_prediction-0.0.7.dist-info/WHEEL
fastapi_advertising_prediction-0.0.7.dist-info/top_level.txt
fastapi_advertising_prediction-0.0.7.dist-info/RECORD
