Metadata-Version: 2.1
Name: fastapi-advertising-prediction
Version: 0.0.7
Summary: ML model deployment of Advertising dataset.
Home-page: https://github.com/erkansirin78/fastapi-advertising-prediction
Author: Erkan SIRIN
Author-email: erkansirin.datalonga@gmail.com
Classifier: Programming Language :: Python :: 3
Classifier: License :: OSI Approved :: MIT License
Classifier: Operating System :: OS Independent
Requires-Python: >=3.7
License-File: LICENSE
